logging_tree/__init__.py
logging_tree/format.py
logging_tree/nodes.py
logging_tree/tests/__init__.py
logging_tree/tests/case.py
logging_tree/tests/test_format.py
logging_tree/tests/test_node.py
logging_tree-1.9.dist-info/METADATA
logging_tree-1.9.dist-info/WHEEL
logging_tree-1.9.dist-info/top_level.txt
logging_tree-1.9.dist-info/RECORD
